<?xml version="1.0" encoding="UTF-8"?>
<!--Taxonomy Linkbase File created by Certent CDM HD version: 21.3.5-->
<link:linkbase xmlns:link="http://www.xbrl.org/2003/linkbase" xmlns:xs="http://www.w3.org/2001/XMLSchema" xmlns:xbrli="http://www.xbrl.org/2003/instance" xmlns:xbrldt="http://xbrl.org/2005/xbrldt" xmlns:xlink="http://www.w3.org/1999/xlink" xmlns:xsi="http://www.w3.org/2001/XMLSchema-instance" xsi:schemaLocation="http://www.xbrl.org/2003/linkbase http://www.xbrl.org/2003/xbrl-linkbase-2003-12-31.xsd">
  <link:roleRef xlink:href="ses-2021-12-31.xsd#ias_1_role-210000_extended" roleURI="http://www.esma.europa.eu/xbrl/role/all/ias_1_role-210000_extended" xlink:type="simple"></link:roleRef>
  <link:roleRef xlink:href="ses-2021-12-31.xsd#ias_1_role-320000_extended" roleURI="http://www.esma.europa.eu/xbrl/role/all/ias_1_role-320000_extended" xlink:type="simple"></link:roleRef>
  <link:roleRef xlink:href="ses-2021-12-31.xsd#ias_1_role-410000_extended" roleURI="http://www.esma.europa.eu/xbrl/role/all/ias_1_role-410000_extended" xlink:type="simple"></link:roleRef>
  <link:roleRef xlink:href="ses-2021-12-31.xsd#ias_1_role-610000_extended" roleURI="http://www.esma.europa.eu/xbrl/role/all/ias_1_role-610000_extended" xlink:type="simple"></link:roleRef>
  <link:roleRef xlink:href="ses-2021-12-31.xsd#ias_7_role-520000_extended" roleURI="http://www.esma.europa.eu/xbrl/role/all/ias_7_role-520000_extended" xlink:type="simple"></link:roleRef>
  <link:calculationLink xlink:type="extended" xlink:role="http://www.esma.europa.eu/xbrl/role/all/ias_1_role-210000_extended">
    <link:loc xlink:type="locator" xlink:href="http://xbrl.ifrs.org/taxonomy/2020-03-16/full_ifrs/full_ifrs-cor_2020-03-16.xsd#ifrs-full_Assets" xlink:label="loc_ifrs-full_Assets_0"></link:loc>
    <link:loc xlink:type="locator" xlink:href="http://xbrl.ifrs.org/taxonomy/2020-03-16/full_ifrs/full_ifrs-cor_2020-03-16.xsd#ifrs-full_NoncurrentAssets" xlink:label="loc_ifrs-full_NoncurrentAssets_0"></link:loc>
    <link:calculationArc xlink:type="arc" priority="0" order="1.0" use="optional" weight="1" xlink:arcrole="http://www.xbrl.org/2003/arcrole/summation-item" xlink:from="loc_ifrs-full_Assets_0" xlink:to="loc_ifrs-full_NoncurrentAssets_0"></link:calculationArc>
    <link:loc xlink:type="locator" xlink:href="http://xbrl.ifrs.org/taxonomy/2020-03-16/full_ifrs/full_ifrs-cor_2020-03-16.xsd#ifrs-full_CurrentAssets" xlink:label="loc_ifrs-full_CurrentAssets_0"></link:loc>
    <link:calculationArc xlink:type="arc" priority="0" order="2.0" use="optional" weight="1" xlink:arcrole="http://www.xbrl.org/2003/arcrole/summation-item" xlink:from="loc_ifrs-full_Assets_0" xlink:to="loc_ifrs-full_CurrentAssets_0"></link:calculationArc>
    <link:loc xlink:type="locator" xlink:href="http://xbrl.ifrs.org/taxonomy/2020-03-16/full_ifrs/full_ifrs-cor_2020-03-16.xsd#ifrs-full_EquityAndLiabilities" xlink:label="loc_ifrs-full_EquityAndLiabilities_0"></link:loc>
    <link:loc xlink:type="locator" xlink:href="http://xbrl.ifrs.org/taxonomy/2020-03-16/full_ifrs/full_ifrs-cor_2020-03-16.xsd#ifrs-full_Equity" xlink:label="loc_ifrs-full_Equity_0"></link:loc>
    <link:calculationArc xlink:type="arc" priority="0" order="3.0" use="optional" weight="1" xlink:arcrole="http://www.xbrl.org/2003/arcrole/summation-item" xlink:from="loc_ifrs-full_EquityAndLiabilities_0" xlink:to="loc_ifrs-full_Equity_0"></link:calculationArc>
    <link:loc xlink:type="locator" xlink:href="http://xbrl.ifrs.org/taxonomy/2020-03-16/full_ifrs/full_ifrs-cor_2020-03-16.xsd#ifrs-full_Liabilities" xlink:label="loc_ifrs-full_Liabilities_0"></link:loc>
    <link:calculationArc xlink:type="arc" priority="0" order="4.0" use="optional" weight="1" xlink:arcrole="http://www.xbrl.org/2003/arcrole/summation-item" xlink:from="loc_ifrs-full_EquityAndLiabilities_0" xlink:to="loc_ifrs-full_Liabilities_0"></link:calculationArc>
    <link:loc xlink:type="locator" xlink:href="http://xbrl.ifrs.org/taxonomy/2020-03-16/full_ifrs/full_ifrs-cor_2020-03-16.xsd#ifrs-full_PropertyPlantAndEquipment" xlink:label="loc_ifrs-full_PropertyPlantAndEquipment_0"></link:loc>
    <link:calculationArc xlink:type="arc" priority="0" order="5.0" use="optional" weight="1" xlink:arcrole="http://www.xbrl.org/2003/arcrole/summation-item" xlink:from="loc_ifrs-full_NoncurrentAssets_0" xlink:to="loc_ifrs-full_PropertyPlantAndEquipment_0"></link:calculationArc>
    <link:loc xlink:type="locator" xlink:href="http://xbrl.ifrs.org/taxonomy/2020-03-16/full_ifrs/full_ifrs-cor_2020-03-16.xsd#ifrs-full_IntangibleAssetsOtherThanGoodwill" xlink:label="loc_ifrs-full_IntangibleAssetsOtherThanGoodwill_0"></link:loc>
    <link:calculationArc xlink:type="arc" priority="0" order="6.0" use="optional" weight="1" xlink:arcrole="http://www.xbrl.org/2003/arcrole/summation-item" xlink:from="loc_ifrs-full_NoncurrentAssets_0" xlink:to="loc_ifrs-full_IntangibleAssetsOtherThanGoodwill_0"></link:calculationArc>
    <link:loc xlink:type="locator" xlink:href="http://xbrl.ifrs.org/taxonomy/2020-03-16/full_ifrs/full_ifrs-cor_2020-03-16.xsd#ifrs-full_DeferredTaxAssets" xlink:label="loc_ifrs-full_DeferredTaxAssets_0"></link:loc>
    <link:calculationArc xlink:type="arc" priority="0" order="7.0" use="optional" weight="1" xlink:arcrole="http://www.xbrl.org/2003/arcrole/summation-item" xlink:from="loc_ifrs-full_NoncurrentAssets_0" xlink:to="loc_ifrs-full_DeferredTaxAssets_0"></link:calculationArc>
    <link:loc xlink:type="locator" xlink:href="http://xbrl.ifrs.org/taxonomy/2020-03-16/full_ifrs/full_ifrs-cor_2020-03-16.xsd#ifrs-full_OtherNoncurrentFinancialAssets" xlink:label="loc_ifrs-full_OtherNoncurrentFinancialAssets_0"></link:loc>
    <link:calculationArc xlink:type="arc" priority="0" order="8.0" use="optional" weight="1" xlink:arcrole="http://www.xbrl.org/2003/arcrole/summation-item" xlink:from="loc_ifrs-full_NoncurrentAssets_0" xlink:to="loc_ifrs-full_OtherNoncurrentFinancialAssets_0"></link:calculationArc>
    <link:loc xlink:type="locator" xlink:href="http://xbrl.ifrs.org/taxonomy/2020-03-16/full_ifrs/full_ifrs-cor_2020-03-16.xsd#ifrs-full_NoncurrentValueAddedTaxReceivables" xlink:label="loc_ifrs-full_NoncurrentValueAddedTaxReceivables_0"></link:loc>
    <link:calculationArc xlink:type="arc" priority="0" order="9.0" use="optional" weight="1" xlink:arcrole="http://www.xbrl.org/2003/arcrole/summation-item" xlink:from="loc_ifrs-full_NoncurrentAssets_0" xlink:to="loc_ifrs-full_NoncurrentValueAddedTaxReceivables_0"></link:calculationArc>
    <link:loc xlink:type="locator" xlink:href="ses-2021-12-31.xsd#SES_PohladavkyZaZadrzne" xlink:label="loc_SES_PohladavkyZaZadrzne_0"></link:loc>
    <link:calculationArc xlink:type="arc" priority="0" order="10.0" use="optional" weight="1" xlink:arcrole="http://www.xbrl.org/2003/arcrole/summation-item" xlink:from="loc_ifrs-full_NoncurrentAssets_0" xlink:to="loc_SES_PohladavkyZaZadrzne_0"></link:calculationArc>
    <link:loc xlink:type="locator" xlink:href="http://xbrl.ifrs.org/taxonomy/2020-03-16/full_ifrs/full_ifrs-cor_2020-03-16.xsd#ifrs-full_NoncurrentAssetsOrDisposalGroupsClassifiedAsHeldForSale" xlink:label="loc_ifrs-full_NoncurrentAssetsOrDisposalGroupsClassifiedAsHeldForSale_0"></link:loc>
    <link:calculationArc xlink:type="arc" priority="0" order="11.0" use="optional" weight="1" xlink:arcrole="http://www.xbrl.org/2003/arcrole/summation-item" xlink:from="loc_ifrs-full_CurrentAssets_0" xlink:to="loc_ifrs-full_NoncurrentAssetsOrDisposalGroupsClassifiedAsHeldForSale_0"></link:calculationArc>
    <link:loc xlink:type="locator" xlink:href="http://xbrl.ifrs.org/taxonomy/2020-03-16/full_ifrs/full_ifrs-cor_2020-03-16.xsd#ifrs-full_Inventories" xlink:label="loc_ifrs-full_Inventories_0"></link:loc>
    <link:calculationArc xlink:type="arc" priority="0" order="12.0" use="optional" weight="1" xlink:arcrole="http://www.xbrl.org/2003/arcrole/summation-item" xlink:from="loc_ifrs-full_CurrentAssets_0" xlink:to="loc_ifrs-full_Inventories_0"></link:calculationArc>
    <link:loc xlink:type="locator" xlink:href="http://xbrl.ifrs.org/taxonomy/2020-03-16/full_ifrs/full_ifrs-cor_2020-03-16.xsd#ifrs-full_CurrentTaxAssetsCurrent" xlink:label="loc_ifrs-full_CurrentTaxAssetsCurrent_0"></link:loc>
    <link:calculationArc xlink:type="arc" priority="0" order="13.0" use="optional" weight="1" xlink:arcrole="http://www.xbrl.org/2003/arcrole/summation-item" xlink:from="loc_ifrs-full_CurrentAssets_0" xlink:to="loc_ifrs-full_CurrentTaxAssetsCurrent_0"></link:calculationArc>
    <link:loc xlink:type="locator" xlink:href="http://xbrl.ifrs.org/taxonomy/2020-03-16/full_ifrs/full_ifrs-cor_2020-03-16.xsd#ifrs-full_CashAndCashEquivalents" xlink:label="loc_ifrs-full_CashAndCashEquivalents_0"></link:loc>
    <link:calculationArc xlink:type="arc" priority="0" order="14.0" use="optional" weight="1" xlink:arcrole="http://www.xbrl.org/2003/arcrole/summation-item" xlink:from="loc_ifrs-full_CurrentAssets_0" xlink:to="loc_ifrs-full_CashAndCashEquivalents_0"></link:calculationArc>
    <link:loc xlink:type="locator" xlink:href="http://xbrl.ifrs.org/taxonomy/2020-03-16/full_ifrs/full_ifrs-cor_2020-03-16.xsd#ifrs-full_CurrentContractAssets" xlink:label="loc_ifrs-full_CurrentContractAssets_0"></link:loc>
    <link:calculationArc xlink:type="arc" priority="0" order="15.0" use="optional" weight="1" xlink:arcrole="http://www.xbrl.org/2003/arcrole/summation-item" xlink:from="loc_ifrs-full_CurrentAssets_0" xlink:to="loc_ifrs-full_CurrentContractAssets_0"></link:calculationArc>
    <link:loc xlink:type="locator" xlink:href="http://xbrl.ifrs.org/taxonomy/2020-03-16/full_ifrs/full_ifrs-cor_2020-03-16.xsd#ifrs-full_CurrentTradeReceivables" xlink:label="loc_ifrs-full_CurrentTradeReceivables_0"></link:loc>
    <link:calculationArc xlink:type="arc" priority="0" order="16.0" use="optional" weight="1" xlink:arcrole="http://www.xbrl.org/2003/arcrole/summation-item" xlink:from="loc_ifrs-full_CurrentAssets_0" xlink:to="loc_ifrs-full_CurrentTradeReceivables_0"></link:calculationArc>
    <link:loc xlink:type="locator" xlink:href="http://xbrl.ifrs.org/taxonomy/2020-03-16/full_ifrs/full_ifrs-cor_2020-03-16.xsd#ifrs-full_OtherCurrentReceivables" xlink:label="loc_ifrs-full_OtherCurrentReceivables_0"></link:loc>
    <link:calculationArc xlink:type="arc" priority="0" order="17.0" use="optional" weight="1" xlink:arcrole="http://www.xbrl.org/2003/arcrole/summation-item" xlink:from="loc_ifrs-full_CurrentAssets_0" xlink:to="loc_ifrs-full_OtherCurrentReceivables_0"></link:calculationArc>
    <link:loc xlink:type="locator" xlink:href="http://xbrl.ifrs.org/taxonomy/2020-03-16/full_ifrs/full_ifrs-cor_2020-03-16.xsd#ifrs-full_EquityAttributableToOwnersOfParent" xlink:label="loc_ifrs-full_EquityAttributableToOwnersOfParent_0"></link:loc>
    <link:calculationArc xlink:type="arc" priority="0" order="18.0" use="optional" weight="1" xlink:arcrole="http://www.xbrl.org/2003/arcrole/summation-item" xlink:from="loc_ifrs-full_Equity_0" xlink:to="loc_ifrs-full_EquityAttributableToOwnersOfParent_0"></link:calculationArc>
    <link:loc xlink:type="locator" xlink:href="http://xbrl.ifrs.org/taxonomy/2020-03-16/full_ifrs/full_ifrs-cor_2020-03-16.xsd#ifrs-full_NoncontrollingInterests" xlink:label="loc_ifrs-full_NoncontrollingInterests_0"></link:loc>
    <link:calculationArc xlink:type="arc" priority="0" order="19.0" use="optional" weight="1" xlink:arcrole="http://www.xbrl.org/2003/arcrole/summation-item" xlink:from="loc_ifrs-full_Equity_0" xlink:to="loc_ifrs-full_NoncontrollingInterests_0"></link:calculationArc>
    <link:loc xlink:type="locator" xlink:href="http://xbrl.ifrs.org/taxonomy/2020-03-16/full_ifrs/full_ifrs-cor_2020-03-16.xsd#ifrs-full_NoncurrentLiabilities" xlink:label="loc_ifrs-full_NoncurrentLiabilities_0"></link:loc>
    <link:calculationArc xlink:type="arc" priority="0" order="20.0" use="optional" weight="1" xlink:arcrole="http://www.xbrl.org/2003/arcrole/summation-item" xlink:from="loc_ifrs-full_Liabilities_0" xlink:to="loc_ifrs-full_NoncurrentLiabilities_0"></link:calculationArc>
    <link:loc xlink:type="locator" xlink:href="http://xbrl.ifrs.org/taxonomy/2020-03-16/full_ifrs/full_ifrs-cor_2020-03-16.xsd#ifrs-full_CurrentLiabilities" xlink:label="loc_ifrs-full_CurrentLiabilities_0"></link:loc>
    <link:calculationArc xlink:type="arc" priority="0" order="21.0" use="optional" weight="1" xlink:arcrole="http://www.xbrl.org/2003/arcrole/summation-item" xlink:from="loc_ifrs-full_Liabilities_0" xlink:to="loc_ifrs-full_CurrentLiabilities_0"></link:calculationArc>
    <link:loc xlink:type="locator" xlink:href="http://xbrl.ifrs.org/taxonomy/2020-03-16/full_ifrs/full_ifrs-cor_2020-03-16.xsd#ifrs-full_IssuedCapital" xlink:label="loc_ifrs-full_IssuedCapital_0"></link:loc>
    <link:calculationArc xlink:type="arc" priority="0" order="22.0" use="optional" weight="1" xlink:arcrole="http://www.xbrl.org/2003/arcrole/summation-item" xlink:from="loc_ifrs-full_EquityAttributableToOwnersOfParent_0" xlink:to="loc_ifrs-full_IssuedCapital_0"></link:calculationArc>
    <link:loc xlink:type="locator" xlink:href="http://xbrl.ifrs.org/taxonomy/2020-03-16/full_ifrs/full_ifrs-cor_2020-03-16.xsd#ifrs-full_RetainedEarnings" xlink:label="loc_ifrs-full_RetainedEarnings_0"></link:loc>
    <link:calculationArc xlink:type="arc" priority="0" order="23.0" use="optional" weight="1" xlink:arcrole="http://www.xbrl.org/2003/arcrole/summation-item" xlink:from="loc_ifrs-full_EquityAttributableToOwnersOfParent_0" xlink:to="loc_ifrs-full_RetainedEarnings_0"></link:calculationArc>
    <link:loc xlink:type="locator" xlink:href="http://xbrl.ifrs.org/taxonomy/2020-03-16/full_ifrs/full_ifrs-cor_2020-03-16.xsd#ifrs-full_StatutoryReserve" xlink:label="loc_ifrs-full_StatutoryReserve_0"></link:loc>
    <link:calculationArc xlink:type="arc" priority="0" order="24.0" use="optional" weight="1" xlink:arcrole="http://www.xbrl.org/2003/arcrole/summation-item" xlink:from="loc_ifrs-full_EquityAttributableToOwnersOfParent_0" xlink:to="loc_ifrs-full_StatutoryReserve_0"></link:calculationArc>
    <link:loc xlink:type="locator" xlink:href="http://xbrl.ifrs.org/taxonomy/2020-03-16/full_ifrs/full_ifrs-cor_2020-03-16.xsd#ifrs-full_ReserveOfExchangeDifferencesOnTranslation" xlink:label="loc_ifrs-full_ReserveOfExchangeDifferencesOnTranslation_0"></link:loc>
    <link:calculationArc xlink:type="arc" priority="0" order="25.0" use="optional" weight="1" xlink:arcrole="http://www.xbrl.org/2003/arcrole/summation-item" xlink:from="loc_ifrs-full_EquityAttributableToOwnersOfParent_0" xlink:to="loc_ifrs-full_ReserveOfExchangeDifferencesOnTranslation_0"></link:calculationArc>
    <link:loc xlink:type="locator" xlink:href="ses-2021-12-31.xsd#SES_AkcionarskePrispevkyAOcenovacieRozdiely" xlink:label="loc_SES_AkcionarskePrispevkyAOcenovacieRozdiely_0"></link:loc>
    <link:calculationArc xlink:type="arc" priority="0" order="26.0" use="optional" weight="1" xlink:arcrole="http://www.xbrl.org/2003/arcrole/summation-item" xlink:from="loc_ifrs-full_EquityAttributableToOwnersOfParent_0" xlink:to="loc_SES_AkcionarskePrispevkyAOcenovacieRozdiely_0"></link:calculationArc>
    <link:loc xlink:type="locator" xlink:href="http://xbrl.ifrs.org/taxonomy/2020-03-16/full_ifrs/full_ifrs-cor_2020-03-16.xsd#ifrs-full_DeferredTaxLiabilities" xlink:label="loc_ifrs-full_DeferredTaxLiabilities_0"></link:loc>
    <link:calculationArc xlink:type="arc" priority="0" order="27.0" use="optional" weight="1" xlink:arcrole="http://www.xbrl.org/2003/arcrole/summation-item" xlink:from="loc_ifrs-full_NoncurrentLiabilities_0" xlink:to="loc_ifrs-full_DeferredTaxLiabilities_0"></link:calculationArc>
    <link:loc xlink:type="locator" xlink:href="http://xbrl.ifrs.org/taxonomy/2020-03-16/full_ifrs/full_ifrs-cor_2020-03-16.xsd#ifrs-full_OtherNoncurrentLiabilities" xlink:label="loc_ifrs-full_OtherNoncurrentLiabilities_0"></link:loc>
    <link:calculationArc xlink:type="arc" priority="0" order="28.0" use="optional" weight="1" xlink:arcrole="http://www.xbrl.org/2003/arcrole/summation-item" xlink:from="loc_ifrs-full_NoncurrentLiabilities_0" xlink:to="loc_ifrs-full_OtherNoncurrentLiabilities_0"></link:calculationArc>
    <link:loc xlink:type="locator" xlink:href="http://xbrl.ifrs.org/taxonomy/2020-03-16/full_ifrs/full_ifrs-cor_2020-03-16.xsd#ifrs-full_NoncurrentLeaseLiabilities" xlink:label="loc_ifrs-full_NoncurrentLeaseLiabilities_0"></link:loc>
    <link:calculationArc xlink:type="arc" priority="0" order="29.0" use="optional" weight="1" xlink:arcrole="http://www.xbrl.org/2003/arcrole/summation-item" xlink:from="loc_ifrs-full_NoncurrentLiabilities_0" xlink:to="loc_ifrs-full_NoncurrentLeaseLiabilities_0"></link:calculationArc>
    <link:loc xlink:type="locator" xlink:href="http://xbrl.ifrs.org/taxonomy/2020-03-16/full_ifrs/full_ifrs-cor_2020-03-16.xsd#ifrs-full_LongtermBorrowings" xlink:label="loc_ifrs-full_LongtermBorrowings_0"></link:loc>
    <link:calculationArc xlink:type="arc" priority="0" order="30.0" use="optional" weight="1" xlink:arcrole="http://www.xbrl.org/2003/arcrole/summation-item" xlink:from="loc_ifrs-full_NoncurrentLiabilities_0" xlink:to="loc_ifrs-full_LongtermBorrowings_0"></link:calculationArc>
    <link:loc xlink:type="locator" xlink:href="http://xbrl.ifrs.org/taxonomy/2020-03-16/full_ifrs/full_ifrs-cor_2020-03-16.xsd#ifrs-full_NoncurrentProvisionsForEmployeeBenefits" xlink:label="loc_ifrs-full_NoncurrentProvisionsForEmployeeBenefits_0"></link:loc>
    <link:calculationArc xlink:type="arc" priority="0" order="31.0" use="optional" weight="1" xlink:arcrole="http://www.xbrl.org/2003/arcrole/summation-item" xlink:from="loc_ifrs-full_NoncurrentLiabilities_0" xlink:to="loc_ifrs-full_NoncurrentProvisionsForEmployeeBenefits_0"></link:calculationArc>
    <link:loc xlink:type="locator" xlink:href="http://xbrl.ifrs.org/taxonomy/2020-03-16/full_ifrs/full_ifrs-cor_2020-03-16.xsd#ifrs-full_CurrentProvisions" xlink:label="loc_ifrs-full_CurrentProvisions_0"></link:loc>
    <link:calculationArc xlink:type="arc" priority="0" order="32.0" use="optional" weight="1" xlink:arcrole="http://www.xbrl.org/2003/arcrole/summation-item" xlink:from="loc_ifrs-full_CurrentLiabilities_0" xlink:to="loc_ifrs-full_CurrentProvisions_0"></link:calculationArc>
    <link:loc xlink:type="locator" xlink:href="http://xbrl.ifrs.org/taxonomy/2020-03-16/full_ifrs/full_ifrs-cor_2020-03-16.xsd#ifrs-full_TradeAndOtherCurrentPayables" xlink:label="loc_ifrs-full_TradeAndOtherCurrentPayables_0"></link:loc>
    <link:calculationArc xlink:type="arc" priority="0" order="33.0" use="optional" weight="1" xlink:arcrole="http://www.xbrl.org/2003/arcrole/summation-item" xlink:from="loc_ifrs-full_CurrentLiabilities_0" xlink:to="loc_ifrs-full_TradeAndOtherCurrentPayables_0"></link:calculationArc>
    <link:loc xlink:type="locator" xlink:href="http://xbrl.ifrs.org/taxonomy/2020-03-16/full_ifrs/full_ifrs-cor_2020-03-16.xsd#ifrs-full_CurrentTaxLiabilitiesCurrent" xlink:label="loc_ifrs-full_CurrentTaxLiabilitiesCurrent_0"></link:loc>
    <link:calculationArc xlink:type="arc" priority="0" order="34.0" use="optional" weight="1" xlink:arcrole="http://www.xbrl.org/2003/arcrole/summation-item" xlink:from="loc_ifrs-full_CurrentLiabilities_0" xlink:to="loc_ifrs-full_CurrentTaxLiabilitiesCurrent_0"></link:calculationArc>
    <link:loc xlink:type="locator" xlink:href="http://xbrl.ifrs.org/taxonomy/2020-03-16/full_ifrs/full_ifrs-cor_2020-03-16.xsd#ifrs-full_CurrentContractLiabilities" xlink:label="loc_ifrs-full_CurrentContractLiabilities_0"></link:loc>
    <link:calculationArc xlink:type="arc" priority="0" order="35.0" use="optional" weight="1" xlink:arcrole="http://www.xbrl.org/2003/arcrole/summation-item" xlink:from="loc_ifrs-full_CurrentLiabilities_0" xlink:to="loc_ifrs-full_CurrentContractLiabilities_0"></link:calculationArc>
    <link:loc xlink:type="locator" xlink:href="http://xbrl.ifrs.org/taxonomy/2020-03-16/full_ifrs/full_ifrs-cor_2020-03-16.xsd#ifrs-full_CurrentLeaseLiabilities" xlink:label="loc_ifrs-full_CurrentLeaseLiabilities_0"></link:loc>
    <link:calculationArc xlink:type="arc" priority="0" order="36.0" use="optional" weight="1" xlink:arcrole="http://www.xbrl.org/2003/arcrole/summation-item" xlink:from="loc_ifrs-full_CurrentLiabilities_0" xlink:to="loc_ifrs-full_CurrentLeaseLiabilities_0"></link:calculationArc>
    <link:loc xlink:type="locator" xlink:href="http://xbrl.ifrs.org/taxonomy/2020-03-16/full_ifrs/full_ifrs-cor_2020-03-16.xsd#ifrs-full_ShorttermBorrowings" xlink:label="loc_ifrs-full_ShorttermBorrowings_0"></link:loc>
    <link:calculationArc xlink:type="arc" priority="0" order="37.0" use="optional" weight="1" xlink:arcrole="http://www.xbrl.org/2003/arcrole/summation-item" xlink:from="loc_ifrs-full_CurrentLiabilities_0" xlink:to="loc_ifrs-full_ShorttermBorrowings_0"></link:calculationArc>
    <link:loc xlink:type="locator" xlink:href="http://xbrl.ifrs.org/taxonomy/2020-03-16/full_ifrs/full_ifrs-cor_2020-03-16.xsd#ifrs-full_OtherCurrentLiabilities" xlink:label="loc_ifrs-full_OtherCurrentLiabilities_0"></link:loc>
    <link:calculationArc xlink:type="arc" priority="0" order="38.0" use="optional" weight="1" xlink:arcrole="http://www.xbrl.org/2003/arcrole/summation-item" xlink:from="loc_ifrs-full_CurrentLiabilities_0" xlink:to="loc_ifrs-full_OtherCurrentLiabilities_0"></link:calculationArc>
    <link:loc xlink:type="locator" xlink:href="http://xbrl.ifrs.org/taxonomy/2020-03-16/full_ifrs/full_ifrs-cor_2020-03-16.xsd#ifrs-full_DeferredIncomeClassifiedAsCurrent" xlink:label="loc_ifrs-full_DeferredIncomeClassifiedAsCurrent_0"></link:loc>
    <link:calculationArc xlink:type="arc" priority="0" order="39.0" use="optional" weight="1" xlink:arcrole="http://www.xbrl.org/2003/arcrole/summation-item" xlink:from="loc_ifrs-full_CurrentLiabilities_0" xlink:to="loc_ifrs-full_DeferredIncomeClassifiedAsCurrent_0"></link:calculationArc>
  </link:calculationLink>
  <link:calculationLink xlink:type="extended" xlink:role="http://www.esma.europa.eu/xbrl/role/all/ias_1_role-320000_extended">
    <link:loc xlink:type="locator" xlink:href="http://xbrl.ifrs.org/taxonomy/2020-03-16/full_ifrs/full_ifrs-cor_2020-03-16.xsd#ifrs-full_ProfitLoss" xlink:label="loc_ifrs-full_ProfitLoss_0"></link:loc>
    <link:loc xlink:type="locator" xlink:href="http://xbrl.ifrs.org/taxonomy/2020-03-16/full_ifrs/full_ifrs-cor_2020-03-16.xsd#ifrs-full_ProfitLossFromContinuingOperations" xlink:label="loc_ifrs-full_ProfitLossFromContinuingOperations_0"></link:loc>
    <link:calculationArc xlink:type="arc" priority="0" order="1.0" use="optional" weight="1" xlink:arcrole="http://www.xbrl.org/2003/arcrole/summation-item" xlink:from="loc_ifrs-full_ProfitLoss_0" xlink:to="loc_ifrs-full_ProfitLossFromContinuingOperations_0"></link:calculationArc>
    <link:loc xlink:type="locator" xlink:href="http://xbrl.ifrs.org/taxonomy/2020-03-16/full_ifrs/full_ifrs-cor_2020-03-16.xsd#ifrs-full_ProfitLossBeforeTax" xlink:label="loc_ifrs-full_ProfitLossBeforeTax_0"></link:loc>
    <link:calculationArc xlink:type="arc" priority="0" order="2.0" use="optional" weight="1" xlink:arcrole="http://www.xbrl.org/2003/arcrole/summation-item" xlink:from="loc_ifrs-full_ProfitLossFromContinuingOperations_0" xlink:to="loc_ifrs-full_ProfitLossBeforeTax_0"></link:calculationArc>
    <link:loc xlink:type="locator" xlink:href="http://xbrl.ifrs.org/taxonomy/2020-03-16/full_ifrs/full_ifrs-cor_2020-03-16.xsd#ifrs-full_IncomeTaxExpenseContinuingOperations" xlink:label="loc_ifrs-full_IncomeTaxExpenseContinuingOperations_0"></link:loc>
    <link:calculationArc xlink:type="arc" priority="0" order="3.0" use="optional" weight="-1" xlink:arcrole="http://www.xbrl.org/2003/arcrole/summation-item" xlink:from="loc_ifrs-full_ProfitLossFromContinuingOperations_0" xlink:to="loc_ifrs-full_IncomeTaxExpenseContinuingOperations_0"></link:calculationArc>
    <link:loc xlink:type="locator" xlink:href="http://xbrl.ifrs.org/taxonomy/2020-03-16/full_ifrs/full_ifrs-cor_2020-03-16.xsd#ifrs-full_FinanceIncomeCost" xlink:label="loc_ifrs-full_FinanceIncomeCost_0"></link:loc>
    <link:calculationArc xlink:type="arc" priority="0" order="4.0" use="optional" weight="1" xlink:arcrole="http://www.xbrl.org/2003/arcrole/summation-item" xlink:from="loc_ifrs-full_ProfitLossBeforeTax_0" xlink:to="loc_ifrs-full_FinanceIncomeCost_0"></link:calculationArc>
    <link:loc xlink:type="locator" xlink:href="http://xbrl.ifrs.org/taxonomy/2020-03-16/full_ifrs/full_ifrs-cor_2020-03-16.xsd#ifrs-full_OperatingExpense" xlink:label="loc_ifrs-full_OperatingExpense_0"></link:loc>
    <link:calculationArc xlink:type="arc" priority="0" order="5.0" use="optional" weight="-1" xlink:arcrole="http://www.xbrl.org/2003/arcrole/summation-item" xlink:from="loc_ifrs-full_ProfitLossBeforeTax_0" xlink:to="loc_ifrs-full_OperatingExpense_0"></link:calculationArc>
    <link:loc xlink:type="locator" xlink:href="http://xbrl.ifrs.org/taxonomy/2020-03-16/full_ifrs/full_ifrs-cor_2020-03-16.xsd#ifrs-full_GainsLossesOnDisposalsOfPropertyPlantAndEquipment" xlink:label="loc_ifrs-full_GainsLossesOnDisposalsOfPropertyPlantAndEquipment_0"></link:loc>
    <link:calculationArc xlink:type="arc" priority="0" order="6.0" use="optional" weight="1" xlink:arcrole="http://www.xbrl.org/2003/arcrole/summation-item" xlink:from="loc_ifrs-full_ProfitLossBeforeTax_0" xlink:to="loc_ifrs-full_GainsLossesOnDisposalsOfPropertyPlantAndEquipment_0"></link:calculationArc>
    <link:loc xlink:type="locator" xlink:href="http://xbrl.ifrs.org/taxonomy/2020-03-16/full_ifrs/full_ifrs-cor_2020-03-16.xsd#ifrs-full_Revenue" xlink:label="loc_ifrs-full_Revenue_0"></link:loc>
    <link:calculationArc xlink:type="arc" priority="0" order="7.0" use="optional" weight="1" xlink:arcrole="http://www.xbrl.org/2003/arcrole/summation-item" xlink:from="loc_ifrs-full_ProfitLossBeforeTax_0" xlink:to="loc_ifrs-full_Revenue_0"></link:calculationArc>
    <link:loc xlink:type="locator" xlink:href="http://xbrl.ifrs.org/taxonomy/2020-03-16/full_ifrs/full_ifrs-cor_2020-03-16.xsd#ifrs-full_CurrentTaxExpenseIncome" xlink:label="loc_ifrs-full_CurrentTaxExpenseIncome_0"></link:loc>
    <link:calculationArc xlink:type="arc" priority="0" order="8.0" use="optional" weight="1" xlink:arcrole="http://www.xbrl.org/2003/arcrole/summation-item" xlink:from="loc_ifrs-full_IncomeTaxExpenseContinuingOperations_0" xlink:to="loc_ifrs-full_CurrentTaxExpenseIncome_0"></link:calculationArc>
    <link:loc xlink:type="locator" xlink:href="http://xbrl.ifrs.org/taxonomy/2020-03-16/full_ifrs/full_ifrs-cor_2020-03-16.xsd#ifrs-full_DeferredTaxExpenseIncomeRecognisedInProfitOrLoss" xlink:label="loc_ifrs-full_DeferredTaxExpenseIncomeRecognisedInProfitOrLoss_0"></link:loc>
    <link:calculationArc xlink:type="arc" priority="0" order="9.0" use="optional" weight="1" xlink:arcrole="http://www.xbrl.org/2003/arcrole/summation-item" xlink:from="loc_ifrs-full_IncomeTaxExpenseContinuingOperations_0" xlink:to="loc_ifrs-full_DeferredTaxExpenseIncomeRecognisedInProfitOrLoss_0"></link:calculationArc>
    <link:loc xlink:type="locator" xlink:href="http://xbrl.ifrs.org/taxonomy/2020-03-16/full_ifrs/full_ifrs-cor_2020-03-16.xsd#ifrs-full_FinanceIncome" xlink:label="loc_ifrs-full_FinanceIncome_0"></link:loc>
    <link:calculationArc xlink:type="arc" priority="0" order="10.0" use="optional" weight="1" xlink:arcrole="http://www.xbrl.org/2003/arcrole/summation-item" xlink:from="loc_ifrs-full_FinanceIncomeCost_0" xlink:to="loc_ifrs-full_FinanceIncome_0"></link:calculationArc>
    <link:loc xlink:type="locator" xlink:href="http://xbrl.ifrs.org/taxonomy/2020-03-16/full_ifrs/full_ifrs-cor_2020-03-16.xsd#ifrs-full_FinanceCosts" xlink:label="loc_ifrs-full_FinanceCosts_0"></link:loc>
    <link:calculationArc xlink:type="arc" priority="0" order="11.0" use="optional" weight="-1" xlink:arcrole="http://www.xbrl.org/2003/arcrole/summation-item" xlink:from="loc_ifrs-full_FinanceIncomeCost_0" xlink:to="loc_ifrs-full_FinanceCosts_0"></link:calculationArc>
    <link:loc xlink:type="locator" xlink:href="http://xbrl.ifrs.org/taxonomy/2020-03-16/full_ifrs/full_ifrs-cor_2020-03-16.xsd#ifrs-full_RawMaterialsAndConsumablesUsed" xlink:label="loc_ifrs-full_RawMaterialsAndConsumablesUsed_0"></link:loc>
    <link:calculationArc xlink:type="arc" priority="0" order="12.0" use="optional" weight="1" xlink:arcrole="http://www.xbrl.org/2003/arcrole/summation-item" xlink:from="loc_ifrs-full_OperatingExpense_0" xlink:to="loc_ifrs-full_RawMaterialsAndConsumablesUsed_0"></link:calculationArc>
    <link:loc xlink:type="locator" xlink:href="http://xbrl.ifrs.org/taxonomy/2020-03-16/full_ifrs/full_ifrs-cor_2020-03-16.xsd#ifrs-full_ServicesExpense" xlink:label="loc_ifrs-full_ServicesExpense_0"></link:loc>
    <link:calculationArc xlink:type="arc" priority="0" order="13.0" use="optional" weight="1" xlink:arcrole="http://www.xbrl.org/2003/arcrole/summation-item" xlink:from="loc_ifrs-full_OperatingExpense_0" xlink:to="loc_ifrs-full_ServicesExpense_0"></link:calculationArc>
    <link:loc xlink:type="locator" xlink:href="http://xbrl.ifrs.org/taxonomy/2020-03-16/full_ifrs/full_ifrs-cor_2020-03-16.xsd#ifrs-full_DepreciationAndAmortisationExpense" xlink:label="loc_ifrs-full_DepreciationAndAmortisationExpense_0"></link:loc>
    <link:calculationArc xlink:type="arc" priority="0" order="14.0" use="optional" weight="1" xlink:arcrole="http://www.xbrl.org/2003/arcrole/summation-item" xlink:from="loc_ifrs-full_OperatingExpense_0" xlink:to="loc_ifrs-full_DepreciationAndAmortisationExpense_0"></link:calculationArc>
    <link:loc xlink:type="locator" xlink:href="http://xbrl.ifrs.org/taxonomy/2020-03-16/full_ifrs/full_ifrs-cor_2020-03-16.xsd#ifrs-full_OtherExpenseByNature" xlink:label="loc_ifrs-full_OtherExpenseByNature_0"></link:loc>
    <link:calculationArc xlink:type="arc" priority="0" order="15.0" use="optional" weight="1" xlink:arcrole="http://www.xbrl.org/2003/arcrole/summation-item" xlink:from="loc_ifrs-full_OperatingExpense_0" xlink:to="loc_ifrs-full_OtherExpenseByNature_0"></link:calculationArc>
    <link:loc xlink:type="locator" xlink:href="http://xbrl.ifrs.org/taxonomy/2020-03-16/full_ifrs/full_ifrs-cor_2020-03-16.xsd#ifrs-full_EmployeeBenefitsExpense" xlink:label="loc_ifrs-full_EmployeeBenefitsExpense_0"></link:loc>
    <link:calculationArc xlink:type="arc" priority="0" order="16.0" use="optional" weight="1" xlink:arcrole="http://www.xbrl.org/2003/arcrole/summation-item" xlink:from="loc_ifrs-full_OperatingExpense_0" xlink:to="loc_ifrs-full_EmployeeBenefitsExpense_0"></link:calculationArc>
    <link:loc xlink:type="locator" xlink:href="http://xbrl.ifrs.org/taxonomy/2020-03-16/full_ifrs/full_ifrs-cor_2020-03-16.xsd#ifrs-full_GainsOnDisposalsOfPropertyPlantAndEquipment" xlink:label="loc_ifrs-full_GainsOnDisposalsOfPropertyPlantAndEquipment_0"></link:loc>
    <link:calculationArc xlink:type="arc" priority="0" order="17.0" use="optional" weight="1" xlink:arcrole="http://www.xbrl.org/2003/arcrole/summation-item" xlink:from="loc_ifrs-full_GainsLossesOnDisposalsOfPropertyPlantAndEquipment_0" xlink:to="loc_ifrs-full_GainsOnDisposalsOfPropertyPlantAndEquipment_0"></link:calculationArc>
    <link:loc xlink:type="locator" xlink:href="http://xbrl.ifrs.org/taxonomy/2020-03-16/full_ifrs/full_ifrs-cor_2020-03-16.xsd#ifrs-full_LossesOnDisposalsOfPropertyPlantAndEquipment" xlink:label="loc_ifrs-full_LossesOnDisposalsOfPropertyPlantAndEquipment_0"></link:loc>
    <link:calculationArc xlink:type="arc" priority="0" order="18.0" use="optional" weight="-1" xlink:arcrole="http://www.xbrl.org/2003/arcrole/summation-item" xlink:from="loc_ifrs-full_GainsLossesOnDisposalsOfPropertyPlantAndEquipment_0" xlink:to="loc_ifrs-full_LossesOnDisposalsOfPropertyPlantAndEquipment_0"></link:calculationArc>
    <link:loc xlink:type="locator" xlink:href="http://xbrl.ifrs.org/taxonomy/2020-03-16/full_ifrs/full_ifrs-cor_2020-03-16.xsd#ifrs-full_RevenueFromRenderingOfServices" xlink:label="loc_ifrs-full_RevenueFromRenderingOfServices_0"></link:loc>
    <link:calculationArc xlink:type="arc" priority="0" order="19.0" use="optional" weight="1" xlink:arcrole="http://www.xbrl.org/2003/arcrole/summation-item" xlink:from="loc_ifrs-full_Revenue_0" xlink:to="loc_ifrs-full_RevenueFromRenderingOfServices_0"></link:calculationArc>
    <link:loc xlink:type="locator" xlink:href="http://xbrl.ifrs.org/taxonomy/2020-03-16/full_ifrs/full_ifrs-cor_2020-03-16.xsd#ifrs-full_OtherRevenue" xlink:label="loc_ifrs-full_OtherRevenue_0"></link:loc>
    <link:calculationArc xlink:type="arc" priority="0" order="20.0" use="optional" weight="1" xlink:arcrole="http://www.xbrl.org/2003/arcrole/summation-item" xlink:from="loc_ifrs-full_Revenue_0" xlink:to="loc_ifrs-full_OtherRevenue_0"></link:calculationArc>
    <link:loc xlink:type="locator" xlink:href="http://xbrl.ifrs.org/taxonomy/2020-03-16/full_ifrs/full_ifrs-cor_2020-03-16.xsd#ifrs-full_RevenueFromConstructionContracts" xlink:label="loc_ifrs-full_RevenueFromConstructionContracts_0"></link:loc>
    <link:calculationArc xlink:type="arc" priority="0" order="21.0" use="optional" weight="1" xlink:arcrole="http://www.xbrl.org/2003/arcrole/summation-item" xlink:from="loc_ifrs-full_Revenue_0" xlink:to="loc_ifrs-full_RevenueFromConstructionContracts_0"></link:calculationArc>
  </link:calculationLink>
  <link:calculationLink xlink:type="extended" xlink:role="http://www.esma.europa.eu/xbrl/role/all/ias_1_role-410000_extended">
    <link:loc xlink:type="locator" xlink:href="http://xbrl.ifrs.org/taxonomy/2020-03-16/full_ifrs/full_ifrs-cor_2020-03-16.xsd#ifrs-full_ComprehensiveIncome" xlink:label="loc_ifrs-full_ComprehensiveIncome_0"></link:loc>
    <link:loc xlink:type="locator" xlink:href="http://xbrl.ifrs.org/taxonomy/2020-03-16/full_ifrs/full_ifrs-cor_2020-03-16.xsd#ifrs-full_ProfitLoss" xlink:label="loc_ifrs-full_ProfitLoss_1"></link:loc>
    <link:calculationArc xlink:type="arc" priority="0" order="1.0" use="optional" weight="1" xlink:arcrole="http://www.xbrl.org/2003/arcrole/summation-item" xlink:from="loc_ifrs-full_ComprehensiveIncome_0" xlink:to="loc_ifrs-full_ProfitLoss_1"></link:calculationArc>
    <link:loc xlink:type="locator" xlink:href="http://xbrl.ifrs.org/taxonomy/2020-03-16/full_ifrs/full_ifrs-cor_2020-03-16.xsd#ifrs-full_OtherComprehensiveIncomeNetOfTaxGainsLossesOnRevaluation" xlink:label="loc_ifrs-full_OtherComprehensiveIncomeNetOfTaxGainsLossesOnRevaluation_0"></link:loc>
    <link:calculationArc xlink:type="arc" priority="0" order="2.0" use="optional" weight="1" xlink:arcrole="http://www.xbrl.org/2003/arcrole/summation-item" xlink:from="loc_ifrs-full_ComprehensiveIncome_0" xlink:to="loc_ifrs-full_OtherComprehensiveIncomeNetOfTaxGainsLossesOnRevaluation_0"></link:calculationArc>
    <link:loc xlink:type="locator" xlink:href="http://xbrl.ifrs.org/taxonomy/2020-03-16/full_ifrs/full_ifrs-cor_2020-03-16.xsd#ifrs-full_ProfitLossAttributableToOwnersOfParent" xlink:label="loc_ifrs-full_ProfitLossAttributableToOwnersOfParent_0"></link:loc>
    <link:calculationArc xlink:type="arc" priority="0" order="3.0" use="optional" weight="1" xlink:arcrole="http://www.xbrl.org/2003/arcrole/summation-item" xlink:from="loc_ifrs-full_ProfitLoss_1" xlink:to="loc_ifrs-full_ProfitLossAttributableToOwnersOfParent_0"></link:calculationArc>
    <link:loc xlink:type="locator" xlink:href="http://xbrl.ifrs.org/taxonomy/2020-03-16/full_ifrs/full_ifrs-cor_2020-03-16.xsd#ifrs-full_ProfitLossAttributableToNoncontrollingInterests" xlink:label="loc_ifrs-full_ProfitLossAttributableToNoncontrollingInterests_0"></link:loc>
    <link:calculationArc xlink:type="arc" priority="0" order="4.0" use="optional" weight="1" xlink:arcrole="http://www.xbrl.org/2003/arcrole/summation-item" xlink:from="loc_ifrs-full_ProfitLoss_1" xlink:to="loc_ifrs-full_ProfitLossAttributableToNoncontrollingInterests_0"></link:calculationArc>
    <link:loc xlink:type="locator" xlink:href="http://xbrl.ifrs.org/taxonomy/2020-03-16/full_ifrs/full_ifrs-cor_2020-03-16.xsd#ifrs-full_GainsLossesOnExchangeDifferencesOnTranslationNetOfTax" xlink:label="loc_ifrs-full_GainsLossesOnExchangeDifferencesOnTranslationNetOfTax_0"></link:loc>
    <link:calculationArc xlink:type="arc" priority="0" order="5.0" use="optional" weight="1" xlink:arcrole="http://www.xbrl.org/2003/arcrole/summation-item" xlink:from="loc_ifrs-full_ComprehensiveIncome_0" xlink:to="loc_ifrs-full_GainsLossesOnExchangeDifferencesOnTranslationNetOfTax_0"></link:calculationArc>
  </link:calculationLink>
  <link:calculationLink xlink:type="extended" xlink:role="http://www.esma.europa.eu/xbrl/role/all/ias_1_role-610000_extended">
    <link:loc xlink:type="locator" xlink:href="http://xbrl.ifrs.org/taxonomy/2020-03-16/full_ifrs/full_ifrs-cor_2020-03-16.xsd#ifrs-full_ComprehensiveIncome" xlink:label="loc_ifrs-full_ComprehensiveIncome_1"></link:loc>
    <link:loc xlink:type="locator" xlink:href="http://xbrl.ifrs.org/taxonomy/2020-03-16/full_ifrs/full_ifrs-cor_2020-03-16.xsd#ifrs-full_ProfitLoss" xlink:label="loc_ifrs-full_ProfitLoss_2"></link:loc>
    <link:calculationArc xlink:type="arc" priority="0" order="1.0" use="optional" weight="1" xlink:arcrole="http://www.xbrl.org/2003/arcrole/summation-item" xlink:from="loc_ifrs-full_ComprehensiveIncome_1" xlink:to="loc_ifrs-full_ProfitLoss_2"></link:calculationArc>
    <link:loc xlink:type="locator" xlink:href="http://xbrl.ifrs.org/taxonomy/2020-03-16/full_ifrs/full_ifrs-cor_2020-03-16.xsd#ifrs-full_IncreaseDecreaseThroughTransferBetweenRevaluationReserveAndRetainedEarnings" xlink:label="loc_ifrs-full_IncreaseDecreaseThroughTransferBetweenRevaluationReserveAndRetainedEarnings_0"></link:loc>
    <link:calculationArc xlink:type="arc" priority="0" order="2.0" use="optional" weight="1" xlink:arcrole="http://www.xbrl.org/2003/arcrole/summation-item" xlink:from="loc_ifrs-full_ComprehensiveIncome_1" xlink:to="loc_ifrs-full_IncreaseDecreaseThroughTransferBetweenRevaluationReserveAndRetainedEarnings_0"></link:calculationArc>
    <link:loc xlink:type="locator" xlink:href="http://xbrl.ifrs.org/taxonomy/2020-03-16/full_ifrs/full_ifrs-cor_2020-03-16.xsd#ifrs-full_GainsLossesOnExchangeDifferencesOnTranslationNetOfTax" xlink:label="loc_ifrs-full_GainsLossesOnExchangeDifferencesOnTranslationNetOfTax_1"></link:loc>
    <link:calculationArc xlink:type="arc" priority="0" order="3.0" use="optional" weight="1" xlink:arcrole="http://www.xbrl.org/2003/arcrole/summation-item" xlink:from="loc_ifrs-full_ComprehensiveIncome_1" xlink:to="loc_ifrs-full_GainsLossesOnExchangeDifferencesOnTranslationNetOfTax_1"></link:calculationArc>
    <link:loc xlink:type="locator" xlink:href="http://xbrl.ifrs.org/taxonomy/2020-03-16/full_ifrs/full_ifrs-cor_2020-03-16.xsd#ifrs-full_OtherComprehensiveIncomeNetOfTaxGainsLossesOnRevaluation" xlink:label="loc_ifrs-full_OtherComprehensiveIncomeNetOfTaxGainsLossesOnRevaluation_1"></link:loc>
    <link:calculationArc xlink:type="arc" priority="0" order="4.0" use="optional" weight="1" xlink:arcrole="http://www.xbrl.org/2003/arcrole/summation-item" xlink:from="loc_ifrs-full_ComprehensiveIncome_1" xlink:to="loc_ifrs-full_OtherComprehensiveIncomeNetOfTaxGainsLossesOnRevaluation_1"></link:calculationArc>
  </link:calculationLink>
  <link:calculationLink xlink:type="extended" xlink:role="http://www.esma.europa.eu/xbrl/role/all/ias_7_role-520000_extended">
    <link:loc xlink:type="locator" xlink:href="http://xbrl.ifrs.org/taxonomy/2020-03-16/full_ifrs/full_ifrs-cor_2020-03-16.xsd#ifrs-full_IncreaseDecreaseInCashAndCashEquivalents" xlink:label="loc_ifrs-full_IncreaseDecreaseInCashAndCashEquivalents_0"></link:loc>
    <link:loc xlink:type="locator" xlink:href="http://xbrl.ifrs.org/taxonomy/2020-03-16/full_ifrs/full_ifrs-cor_2020-03-16.xsd#ifrs-full_CashFlowsFromUsedInOperatingActivities" xlink:label="loc_ifrs-full_CashFlowsFromUsedInOperatingActivities_0"></link:loc>
    <link:calculationArc xlink:type="arc" priority="0" order="1.0" use="optional" weight="1" xlink:arcrole="http://www.xbrl.org/2003/arcrole/summation-item" xlink:from="loc_ifrs-full_IncreaseDecreaseInCashAndCashEquivalents_0" xlink:to="loc_ifrs-full_CashFlowsFromUsedInOperatingActivities_0"></link:calculationArc>
    <link:loc xlink:type="locator" xlink:href="http://xbrl.ifrs.org/taxonomy/2020-03-16/full_ifrs/full_ifrs-cor_2020-03-16.xsd#ifrs-full_CashFlowsFromUsedInInvestingActivities" xlink:label="loc_ifrs-full_CashFlowsFromUsedInInvestingActivities_0"></link:loc>
    <link:calculationArc xlink:type="arc" priority="0" order="2.0" use="optional" weight="1" xlink:arcrole="http://www.xbrl.org/2003/arcrole/summation-item" xlink:from="loc_ifrs-full_IncreaseDecreaseInCashAndCashEquivalents_0" xlink:to="loc_ifrs-full_CashFlowsFromUsedInInvestingActivities_0"></link:calculationArc>
    <link:loc xlink:type="locator" xlink:href="http://xbrl.ifrs.org/taxonomy/2020-03-16/full_ifrs/full_ifrs-cor_2020-03-16.xsd#ifrs-full_CashFlowsFromUsedInFinancingActivities" xlink:label="loc_ifrs-full_CashFlowsFromUsedInFinancingActivities_0"></link:loc>
    <link:calculationArc xlink:type="arc" priority="0" order="3.0" use="optional" weight="1" xlink:arcrole="http://www.xbrl.org/2003/arcrole/summation-item" xlink:from="loc_ifrs-full_IncreaseDecreaseInCashAndCashEquivalents_0" xlink:to="loc_ifrs-full_CashFlowsFromUsedInFinancingActivities_0"></link:calculationArc>
    <link:loc xlink:type="locator" xlink:href="http://xbrl.ifrs.org/taxonomy/2020-03-16/full_ifrs/full_ifrs-cor_2020-03-16.xsd#ifrs-full_InterestPaidClassifiedAsOperatingActivities" xlink:label="loc_ifrs-full_InterestPaidClassifiedAsOperatingActivities_0"></link:loc>
    <link:calculationArc xlink:type="arc" priority="0" order="4.0" use="optional" weight="-1" xlink:arcrole="http://www.xbrl.org/2003/arcrole/summation-item" xlink:from="loc_ifrs-full_CashFlowsFromUsedInOperatingActivities_0" xlink:to="loc_ifrs-full_InterestPaidClassifiedAsOperatingActivities_0"></link:calculationArc>
    <link:loc xlink:type="locator" xlink:href="http://xbrl.ifrs.org/taxonomy/2020-03-16/full_ifrs/full_ifrs-cor_2020-03-16.xsd#ifrs-full_IncomeTaxesPaidRefundClassifiedAsOperatingActivities" xlink:label="loc_ifrs-full_IncomeTaxesPaidRefundClassifiedAsOperatingActivities_0"></link:loc>
    <link:calculationArc xlink:type="arc" priority="0" order="5.0" use="optional" weight="-1" xlink:arcrole="http://www.xbrl.org/2003/arcrole/summation-item" xlink:from="loc_ifrs-full_CashFlowsFromUsedInOperatingActivities_0" xlink:to="loc_ifrs-full_IncomeTaxesPaidRefundClassifiedAsOperatingActivities_0"></link:calculationArc>
    <link:loc xlink:type="locator" xlink:href="http://xbrl.ifrs.org/taxonomy/2020-03-16/full_ifrs/full_ifrs-cor_2020-03-16.xsd#ifrs-full_CashFlowsFromUsedInOperationsBeforeChangesInWorkingCapital" xlink:label="loc_ifrs-full_CashFlowsFromUsedInOperationsBeforeChangesInWorkingCapital_0"></link:loc>
    <link:calculationArc xlink:type="arc" priority="0" order="6.0" use="optional" weight="1" xlink:arcrole="http://www.xbrl.org/2003/arcrole/summation-item" xlink:from="loc_ifrs-full_CashFlowsFromUsedInOperatingActivities_0" xlink:to="loc_ifrs-full_CashFlowsFromUsedInOperationsBeforeChangesInWorkingCapital_0"></link:calculationArc>
    <link:loc xlink:type="locator" xlink:href="http://xbrl.ifrs.org/taxonomy/2020-03-16/full_ifrs/full_ifrs-cor_2020-03-16.xsd#ifrs-full_AdjustmentsForDecreaseIncreaseInInventories" xlink:label="loc_ifrs-full_AdjustmentsForDecreaseIncreaseInInventories_0"></link:loc>
    <link:calculationArc xlink:type="arc" priority="0" order="7.0" use="optional" weight="1" xlink:arcrole="http://www.xbrl.org/2003/arcrole/summation-item" xlink:from="loc_ifrs-full_CashFlowsFromUsedInOperatingActivities_0" xlink:to="loc_ifrs-full_AdjustmentsForDecreaseIncreaseInInventories_0"></link:calculationArc>
    <link:loc xlink:type="locator" xlink:href="http://xbrl.ifrs.org/taxonomy/2020-03-16/full_ifrs/full_ifrs-cor_2020-03-16.xsd#ifrs-full_AdjustmentsForDecreaseIncreaseInTradeAccountReceivable" xlink:label="loc_ifrs-full_AdjustmentsForDecreaseIncreaseInTradeAccountReceivable_0"></link:loc>
    <link:calculationArc xlink:type="arc" priority="0" order="8.0" use="optional" weight="1" xlink:arcrole="http://www.xbrl.org/2003/arcrole/summation-item" xlink:from="loc_ifrs-full_CashFlowsFromUsedInOperatingActivities_0" xlink:to="loc_ifrs-full_AdjustmentsForDecreaseIncreaseInTradeAccountReceivable_0"></link:calculationArc>
    <link:loc xlink:type="locator" xlink:href="http://xbrl.ifrs.org/taxonomy/2020-03-16/full_ifrs/full_ifrs-cor_2020-03-16.xsd#ifrs-full_AdjustmentsForIncreaseDecreaseInTradeAccountPayable" xlink:label="loc_ifrs-full_AdjustmentsForIncreaseDecreaseInTradeAccountPayable_0"></link:loc>
    <link:calculationArc xlink:type="arc" priority="0" order="9.0" use="optional" weight="1" xlink:arcrole="http://www.xbrl.org/2003/arcrole/summation-item" xlink:from="loc_ifrs-full_CashFlowsFromUsedInOperatingActivities_0" xlink:to="loc_ifrs-full_AdjustmentsForIncreaseDecreaseInTradeAccountPayable_0"></link:calculationArc>
    <link:loc xlink:type="locator" xlink:href="http://xbrl.ifrs.org/taxonomy/2020-03-16/full_ifrs/full_ifrs-cor_2020-03-16.xsd#ifrs-full_AdjustmentsForProvisions" xlink:label="loc_ifrs-full_AdjustmentsForProvisions_0"></link:loc>
    <link:calculationArc xlink:type="arc" priority="0" order="10.0" use="optional" weight="1" xlink:arcrole="http://www.xbrl.org/2003/arcrole/summation-item" xlink:from="loc_ifrs-full_CashFlowsFromUsedInOperatingActivities_0" xlink:to="loc_ifrs-full_AdjustmentsForProvisions_0"></link:calculationArc>
    <link:loc xlink:type="locator" xlink:href="ses-2021-12-31.xsd#SES_UpravyOZnizenieZvysenieStavuZakazkovejVyroby" xlink:label="loc_SES_UpravyOZnizenieZvysenieStavuZakazkovejVyroby_0"></link:loc>
    <link:calculationArc xlink:type="arc" priority="0" order="11.0" use="optional" weight="1" xlink:arcrole="http://www.xbrl.org/2003/arcrole/summation-item" xlink:from="loc_ifrs-full_CashFlowsFromUsedInOperatingActivities_0" xlink:to="loc_SES_UpravyOZnizenieZvysenieStavuZakazkovejVyroby_0"></link:calculationArc>
    <link:loc xlink:type="locator" xlink:href="http://xbrl.ifrs.org/taxonomy/2020-03-16/full_ifrs/full_ifrs-cor_2020-03-16.xsd#ifrs-full_ProceedsFromSalesOfPropertyPlantAndEquipmentClassifiedAsInvestingActivities" xlink:label="loc_ifrs-full_ProceedsFromSalesOfPropertyPlantAndEquipmentClassifiedAsInvestingActivities_0"></link:loc>
    <link:calculationArc xlink:type="arc" priority="0" order="12.0" use="optional" weight="1" xlink:arcrole="http://www.xbrl.org/2003/arcrole/summation-item" xlink:from="loc_ifrs-full_CashFlowsFromUsedInInvestingActivities_0" xlink:to="loc_ifrs-full_ProceedsFromSalesOfPropertyPlantAndEquipmentClassifiedAsInvestingActivities_0"></link:calculationArc>
    <link:loc xlink:type="locator" xlink:href="http://xbrl.ifrs.org/taxonomy/2020-03-16/full_ifrs/full_ifrs-cor_2020-03-16.xsd#ifrs-full_PurchaseOfPropertyPlantAndEquipmentIntangibleAssetsOtherThanGoodwillInvestmentPropertyAndOtherNoncurrentAssets" xlink:label="loc_ifrs-full_PurchaseOfPropertyPlantAndEquipmentIntangibleAssetsOtherThanGoodwillInvestmentPropertyAndOtherNoncurrentAssets_0"></link:loc>
    <link:calculationArc xlink:type="arc" priority="0" order="13.0" use="optional" weight="-1" xlink:arcrole="http://www.xbrl.org/2003/arcrole/summation-item" xlink:from="loc_ifrs-full_CashFlowsFromUsedInInvestingActivities_0" xlink:to="loc_ifrs-full_PurchaseOfPropertyPlantAndEquipmentIntangibleAssetsOtherThanGoodwillInvestmentPropertyAndOtherNoncurrentAssets_0"></link:calculationArc>
    <link:loc xlink:type="locator" xlink:href="http://xbrl.ifrs.org/taxonomy/2020-03-16/full_ifrs/full_ifrs-cor_2020-03-16.xsd#ifrs-full_ProceedsFromCurrentBorrowings" xlink:label="loc_ifrs-full_ProceedsFromCurrentBorrowings_0"></link:loc>
    <link:calculationArc xlink:type="arc" priority="0" order="14.0" use="optional" weight="1" xlink:arcrole="http://www.xbrl.org/2003/arcrole/summation-item" xlink:from="loc_ifrs-full_CashFlowsFromUsedInFinancingActivities_0" xlink:to="loc_ifrs-full_ProceedsFromCurrentBorrowings_0"></link:calculationArc>
    <link:loc xlink:type="locator" xlink:href="http://xbrl.ifrs.org/taxonomy/2020-03-16/full_ifrs/full_ifrs-cor_2020-03-16.xsd#ifrs-full_RepaymentsOfCurrentBorrowings" xlink:label="loc_ifrs-full_RepaymentsOfCurrentBorrowings_0"></link:loc>
    <link:calculationArc xlink:type="arc" priority="0" order="15.0" use="optional" weight="-1" xlink:arcrole="http://www.xbrl.org/2003/arcrole/summation-item" xlink:from="loc_ifrs-full_CashFlowsFromUsedInFinancingActivities_0" xlink:to="loc_ifrs-full_RepaymentsOfCurrentBorrowings_0"></link:calculationArc>
    <link:loc xlink:type="locator" xlink:href="http://xbrl.ifrs.org/taxonomy/2020-03-16/full_ifrs/full_ifrs-cor_2020-03-16.xsd#ifrs-full_ProfitLoss" xlink:label="loc_ifrs-full_ProfitLoss_3"></link:loc>
    <link:calculationArc xlink:type="arc" priority="0" order="16.0" use="optional" weight="1" xlink:arcrole="http://www.xbrl.org/2003/arcrole/summation-item" xlink:from="loc_ifrs-full_CashFlowsFromUsedInOperationsBeforeChangesInWorkingCapital_0" xlink:to="loc_ifrs-full_ProfitLoss_3"></link:calculationArc>
    <link:loc xlink:type="locator" xlink:href="http://xbrl.ifrs.org/taxonomy/2020-03-16/full_ifrs/full_ifrs-cor_2020-03-16.xsd#ifrs-full_AdjustmentsForIncomeTaxExpense" xlink:label="loc_ifrs-full_AdjustmentsForIncomeTaxExpense_0"></link:loc>
    <link:calculationArc xlink:type="arc" priority="0" order="17.0" use="optional" weight="1" xlink:arcrole="http://www.xbrl.org/2003/arcrole/summation-item" xlink:from="loc_ifrs-full_CashFlowsFromUsedInOperationsBeforeChangesInWorkingCapital_0" xlink:to="loc_ifrs-full_AdjustmentsForIncomeTaxExpense_0"></link:calculationArc>
    <link:loc xlink:type="locator" xlink:href="http://xbrl.ifrs.org/taxonomy/2020-03-16/full_ifrs/full_ifrs-cor_2020-03-16.xsd#ifrs-full_AdjustmentsForGainLossOnDisposalsPropertyPlantAndEquipment" xlink:label="loc_ifrs-full_AdjustmentsForGainLossOnDisposalsPropertyPlantAndEquipment_0"></link:loc>
    <link:calculationArc xlink:type="arc" priority="0" order="18.0" use="optional" weight="-1" xlink:arcrole="http://www.xbrl.org/2003/arcrole/summation-item" xlink:from="loc_ifrs-full_CashFlowsFromUsedInOperationsBeforeChangesInWorkingCapital_0" xlink:to="loc_ifrs-full_AdjustmentsForGainLossOnDisposalsPropertyPlantAndEquipment_0"></link:calculationArc>
    <link:loc xlink:type="locator" xlink:href="http://xbrl.ifrs.org/taxonomy/2020-03-16/full_ifrs/full_ifrs-cor_2020-03-16.xsd#ifrs-full_AdjustmentsForDepreciationAndAmortisationExpense" xlink:label="loc_ifrs-full_AdjustmentsForDepreciationAndAmortisationExpense_0"></link:loc>
    <link:calculationArc xlink:type="arc" priority="0" order="19.0" use="optional" weight="1" xlink:arcrole="http://www.xbrl.org/2003/arcrole/summation-item" xlink:from="loc_ifrs-full_CashFlowsFromUsedInOperationsBeforeChangesInWorkingCapital_0" xlink:to="loc_ifrs-full_AdjustmentsForDepreciationAndAmortisationExpense_0"></link:calculationArc>
    <link:loc xlink:type="locator" xlink:href="http://xbrl.ifrs.org/taxonomy/2020-03-16/full_ifrs/full_ifrs-cor_2020-03-16.xsd#ifrs-full_AdjustmentsForInterestExpense" xlink:label="loc_ifrs-full_AdjustmentsForInterestExpense_0"></link:loc>
    <link:calculationArc xlink:type="arc" priority="0" order="20.0" use="optional" weight="1" xlink:arcrole="http://www.xbrl.org/2003/arcrole/summation-item" xlink:from="loc_ifrs-full_CashFlowsFromUsedInOperationsBeforeChangesInWorkingCapital_0" xlink:to="loc_ifrs-full_AdjustmentsForInterestExpense_0"></link:calculationArc>
    <link:loc xlink:type="locator" xlink:href="http://xbrl.ifrs.org/taxonomy/2020-03-16/full_ifrs/full_ifrs-cor_2020-03-16.xsd#ifrs-full_AdjustmentsForImpairmentLossReversalOfImpairmentLossRecognisedInProfitOrLossTradeAndOtherReceivables" xlink:label="loc_ifrs-full_AdjustmentsForImpairmentLossReversalOfImpairmentLossRecognisedInProfitOrLossTradeAndOtherReceivables_0"></link:loc>
    <link:calculationArc xlink:type="arc" priority="0" order="21.0" use="optional" weight="1" xlink:arcrole="http://www.xbrl.org/2003/arcrole/summation-item" xlink:from="loc_ifrs-full_CashFlowsFromUsedInOperationsBeforeChangesInWorkingCapital_0" xlink:to="loc_ifrs-full_AdjustmentsForImpairmentLossReversalOfImpairmentLossRecognisedInProfitOrLossTradeAndOtherReceivables_0"></link:calculationArc>
    <link:loc xlink:type="locator" xlink:href="ses-2021-12-31.xsd#SES_UpravyOZvysenieZnizenieOdpisuZavazkov" xlink:label="loc_SES_UpravyOZvysenieZnizenieOdpisuZavazkov_0"></link:loc>
    <link:calculationArc xlink:type="arc" priority="0" order="22.0" use="optional" weight="1" xlink:arcrole="http://www.xbrl.org/2003/arcrole/summation-item" xlink:from="loc_ifrs-full_CashFlowsFromUsedInOperationsBeforeChangesInWorkingCapital_0" xlink:to="loc_SES_UpravyOZvysenieZnizenieOdpisuZavazkov_0"></link:calculationArc>
  </link:calculationLink>
</link:linkbase>